privacy_phone_summarizer/__init__.py
privacy_phone_summarizer/main.py
privacy_phone_summarizer/prompts.py
privacy_phone_summarizer-2025.12.21084113.dist-info/METADATA
privacy_phone_summarizer-2025.12.21084113.dist-info/WHEEL
privacy_phone_summarizer-2025.12.21084113.dist-info/top_level.txt
privacy_phone_summarizer-2025.12.21084113.dist-info/RECORD
