Metadata-Version: 2.4
Name: privacy-phone-summarizer
Version: 2025.12.21084113
Summary: A new package that receives a short textual description of a phone company that deliberately avoids collecting personal data and returns a structured, machine‑readable summary (e.g., JSON) of the serv
Author-email: privacy-phone-summarizer <hi@eugene.plus>
License: MIT
Project-URL: Homepage, https://github.com/chigwell/privacy-phone-summarizer
Requires-Python: >=3.9
Requires-Dist: langchain-llm7>=0.0.0
Requires-Dist: llmatch-messages>=0.0.0
Requires-Dist: langchain-core>=0.3.0
